can_bluetooth/__init__.py
can_bluetooth/_bluetooth_can.py
can_bluetooth/version.py
can_bluetooth_test/__init__.py
can_bluetooth_test/test_interface_bluetooth.py
can_bluetooth_test/test_setup.py
python_can_bluetooth-0.1.3.dist-info/METADATA
python_can_bluetooth-0.1.3.dist-info/WHEEL
python_can_bluetooth-0.1.3.dist-info/entry_points.txt
python_can_bluetooth-0.1.3.dist-info/top_level.txt
python_can_bluetooth-0.1.3.dist-info/RECORD
