Metadata-Version: 2.1
Name: python-can-bluetooth
Version: 0.1.3
Summary: A python-can interface driver for CAN transmitted over a Bluetooth SPP connection
Author-email: Matt Woodhead <woody.w62@gmail.com>
License: GNU Lesser General Public License v3 (LGPLv3)
Project-URL: homepage, https://github.com/MattWoodhead/python-can-bluetooth
Project-URL: documentation, https://github.com/MattWoodhead/python-can-bluetooth
Project-URL: repository, https://github.com/MattWoodhead/python-can-bluetooth
Keywords: CANbus,Bluetooth,python-can,ESP32
Classifier: Development Status :: 3 - Alpha
Classifier: License :: OSI Approved :: GNU Lesser General Public License v3 (LGPLv3)
Classifier: Operating System :: Microsoft :: Windows
Classifier: Programming Language :: Python :: 3
Classifier: Intended Audience :: Developers
Classifier: Intended Audience :: End Users/Desktop
Classifier: Intended Audience :: Manufacturing
Classifier: Environment :: Plugins
Requires-Python: >=3.7
Requires-Dist: python-can
Requires-Dist: pyserial
Provides-Extra: dev
Requires-Dist: windows-curses ; extra == 'dev'
Requires-Dist: parameterized ; extra == 'dev'
Requires-Dist: pytest ; extra == 'dev'
